kaneai/__init__.py
kaneai/actions.py
kaneai/config.py
kaneai/driver.py
kaneai/heal.py
kaneai/safari.py
kaneai/utils.py
kaneai/webdriver_utils.py
kaneai-0.0.25.dist-info/METADATA
kaneai-0.0.25.dist-info/WHEEL
kaneai-0.0.25.dist-info/top_level.txt
kaneai-0.0.25.dist-info/RECORD
