Metadata-Version: 2.4
Name: kaneai
Version: 0.0.25
Summary: A package for UI automation and healing using Selenium
Author-email: Navin Chandra <navinchandra@lambdatest.com>
Project-URL: Homepage, https://github.com/LambdatestIncPrivate/web-kaneai-code-runner
Project-URL: Bug Tracker, https://github.com/LambdatestIncPrivate/web-kaneai-code-runner/issues
Classifier: Programming Language :: Python :: 3
Classifier: Operating System :: OS Independent
Requires-Python: >=3.8
Requires-Dist: selenium>=4.0.0
Requires-Dist: requests>=2.25.1
